{
  "wayto": {
    "10453": "out"
  },
  "paths": [
    "Obvious exits: out"
  ],
  "image_coords": null,
  "terrain": null,
  "description": [
    "Beneath a high arched ceiling, a tattered merchant permit hangs on one of the textured black silk walls.  A twisted dark metal rack and a gold-veined black marble counter sit in opposite corners while a wyvern painted ivory vase rests on a glossy black ebonwood floor."
  ],
  "image": null,
  "climate": null,
  "title": [
    "[Nalatia's Magic Shoppe]"
  ],
  "check_location": null,
  "timeto": {
    "10453": 0.2
  },
  "id": 13613,
  "location": null,
  "tags": [

  ],
  "links": [

  ]
}