{
  "wayto": {
    "14408": "south",
    "5681": "go doors"
  },
  "paths": [
    "Obvious paths: south"
  ],
  "image_coords": null,
  "terrain": null,
  "description": [
    "The stone walls surrounding this courtyard have been built with numerous small shelves jutting out at various heights, while the center of the courtyard is occupied by a crystal clear pond teeming with a school of brightly colored fish.  A monir-planked catwalk spans the pool, bisecting it and providing ample opportunities for nimble-pawed fishing in the moonlight.",
    "The stone walls surrounding this courtyard have been built with numerous small shelves jutting out at various heights, while the center of the courtyard is occupied by a crystal clear pond teeming with a school of brightly colored fish.  A monir-planked catwalk spans the pool, bisecting it and providing ample opportunities for nimble-pawed fishing."
  ],
  "image": null,
  "climate": null,
  "title": [
    "[Andelas' Temple, Pond Courtyard]"
  ],
  "check_location": null,
  "timeto": {
    "14408": 0.2,
    "5681": 0.2
  },
  "id": 14407,
  "location": "the southern part of Solhaven",
  "tags": [

  ],
  "links": [

  ]
}