{
  "wayto": {
    "149": "west",
    "1441": "north",
    "1451": "east"
  },
  "paths": [
    "Obvious paths: north, east, west"
  ],
  "image_coords": [
    1246,
    513,
    1270,
    537
  ],
  "terrain": "hard, flat",
  "description": [
    "Ivy climbs the walls of a stone cottage.  Smoke curls from the chimney, leaving the air heavy with the scent of burning modwir.  An old man sits on the doorstep, whittling a stick."
  ],
  "image": "vo-solhaven-1263764670.png",
  "climate": "temperate",
  "title": [
    "[Solhaven, Triton Road]"
  ],
  "check_location": null,
  "timeto": {
    "149": 0.2,
    "1441": 0.2,
    "1451": 0.2
  },
  "id": 1443,
  "location": "the free port of Solhaven",
  "tags": [
    "no forageables",
    "meta:forage-sensed"
  ],
  "links": [

  ]
}