{
  "id": 15684,
  "title": [
    "[Vortigarn's Magic Shoppe]"
  ],
  "description": [
    "Beneath an oak beam ceiling, a pair of wooden snowshoes hangs on one of the dark oak walls.  A large brass-bound chest and a lacquered wooden shelf sit in opposite corners while a polar bear rug rests on a stained oak floor."
  ],
  "paths": [
    "Obvious exits: north, out"
  ],
  "location": "Icemule Trace",
  "wayto": {
    "3440": "out",
    "15809": "north"
  },
  "timeto": {
    "3440": 0.2,
    "15809": 0.2
  }
}