{
  "id": 16495,
  "title": [
    "[Jaedee's Outfitting]"
  ],
  "description": [
    "Beneath a billowing silk ceiling, a tropical bloom wreath hangs on one of the whitewashed pine walls.  An oversized sea chest and a shell-lined bamboo counter sit in opposite corners while a well-pruned lemon tree rests on a colorful mosaic floor."
  ],
  "paths": [
    "Obvious exits: north, east, out"
  ],
  "location": "Mist Harbor",
  "wayto": {
    "12265": "out",
    "16676": "east",
    "16677": "north"
  },
  "timeto": {
    "12265": 0.2,
    "16676": 0.2,
    "16677": 0.2
  }
}