{
  "wayto": {
    "16863": "west"
  },
  "paths": [
    "Obvious exits: west"
  ],
  "image_coords": null,
  "terrain": null,
  "description": [
    "Hides from a variety of animals lie in piles upon a badly stained counter.  Several vats in the rear of the tannery contain noxious liquids that fill the air with odoriferously offensive fumes.  Splatters cover the stone walls in bizarrely aesthetically pleasing patterns."
  ],
  "image": null,
  "climate": null,
  "title": [
    "[D.H. Cobbling Outlet, Tannery]"
  ],
  "check_location": null,
  "timeto": {
    "16863": 0.2
  },
  "id": 16864,
  "location": "Zul Logoth",
  "tags": [

  ],
  "links": [

  ]
}