{
  "id": 16900,
  "title": [
    "[Multicolor Mushroom, Tunnel]"
  ],
  "description": [
    "Chaotically splattered across the walls, various colored dyes have dripped down the stone, intermingling with one another to a uniform brown near the floor.  A few swathes of canvas are piled in a corner, the remnants of a futile attempt at cleanup."
  ],
  "paths": [
    "Obvious exits: southeast, south, southwest"
  ],
  "location": "Zul Logoth",
  "wayto": {
    "16899": "southeast",
    "16895": "south",
    "16897": "southwest"
  },
  "timeto": {
    "16899": 0.2,
    "16895": 0.2,
    "16897": 0.2
  },
  "image": "en-zul_dyers_tent-1512187947.png",
  "image_coords": [
    1588,
    373,
    1735,
    447
  ]
}