{
  "wayto": {
    "17222": "south",
    "17223": "east",
    "3521": "go gate",
    "17216": "west"
  },
  "paths": [
    "Obvious paths: east, south, west"
  ],
  "image_coords": [
    184,
    165,
    204,
    185
  ],
  "terrain": null,
  "description": [
    "Massive fel and modwir trees tower over the vaalorn-banded gate barring the path.  There looks to be a considerable grove within the enclosure, the trees dense enough to cover whatever might be beyond them."
  ],
  "image": "warrior_guilds-1268684755.png",
  "climate": null,
  "title": [
    "[Warrior Guild, Entryway]"
  ],
  "check_location": null,
  "timeto": {
    "17222": 0.2,
    "17223": 0.2,
    "3521": 0.2,
    "17216": 0.2
  },
  "id": 17215,
  "location": "Ta'Vaalor",
  "tags": [

  ],
  "links": [

  ]
}