{
  "id": 18043,
  "title": [
    "[Wizard Guild, Shaft Base]"
  ],
  "description": [
    "You stand atop a platform of flame-cut granite fashioned into a perfect circle and positioned beneath a shaft, matching in shape and stone, extending far overhead.  Several guild wizards pass through the foyer below in quiet conversation."
  ],
  "paths": [
    "Obvious exits: up"
  ],
  "location": "Ta'Vaalor",
  "wayto": {
    "18052": {
      "file": "string_procs/wayto/18043_18052.rb"
    },
    "18042": "go steps"
  },
  "timeto": {
    "18052": 3.0,
    "18042": 0.2
  }
}