{
  "id": 18235,
  "title": [
    "[Feywrot Mire, Festival Bank]"
  ],
  "description": [
    "Blue-green moss creeps along the upper walls of the structure, which is leaning very slightly to one side.  Where windows once looked out, boards now cover the spaces, and dust, mud, and cobwebs sweep across amlost every surface.  The only clean space is a makeshift teller's cage and a polished silver sign set up in one corner.",
    "Blue-green moss creeps along the upper walls of the structure, which is leaning very slightly to one side.  Where windows once looked out, boards now cover the spaces, and dust, mud, and cobwebs sweep across almost every surface.  The only clean space is a makeshift teller's cage and a polished silver sign set up in one corner."
  ],
  "paths": [
    "Obvious exits: none"
  ],
  "location": "the Feywrot Mire",
  "wayto": {
    "18223": "go arch"
  },
  "timeto": {
    "18223": 0.2
  },
  "tags": [
    "bank"
  ]
}