{
  "wayto": {
    "19540": "southeast",
    "19518": "go stairway",
    "23250": "southwest"
  },
  "paths": [
    "Obvious exits: southeast, southwest"
  ],
  "image_coords": null,
  "terrain": null,
  "description": [
    "Evenly spaced windows line the inner wall, offering a bird's eye view of the hall's lush courtyard.  Pale olive green and ivory tiles form a simple checkered pattern along the floor, curving southward in both directions.",
    "Evenly spaced windows line the inner wall, offering a bird's eye view of the hall's darkened courtyard.  Pale olive green and ivory tiles form a simple checkered pattern along the floor, curving southward in both directions."
  ],
  "image": null,
  "climate": null,
  "title": [
    "[Empath Guild]"
  ],
  "check_location": null,
  "timeto": {
    "19540": 0.2,
    "19518": 0.2,
    "23250": 0.2
  },
  "id": 19519,
  "location": "Ta'Illistim",
  "tags": [

  ],
  "links": [

  ]
}