{
  "wayto": {
    "21099": "northwest"
  },
  "paths": [
    "Obvious paths: northwest"
  ],
  "image_coords": null,
  "terrain": null,
  "description": [
    "Supported by a bough of a cocobolo tree, a low-hanging swing creaks as a slight breeze pushes it over a bed of colorful flowers.  Warm sunlight filters through the leafy cocobolo, leaving checkered patterns of light to illuminate the mossy floor.  Every now and then a monkey or two swings from the branches of a nearby tree to the south, paying little notice to the goings-on below.",
    "Supported by a bough of a cocobolo tree, a low-hanging swing creaks as a slight breeze pushes it over a bed of colorful flowers.  Cool moonlight filters through the leafy cocobolo, leaving checkered patterns of light to illuminate the mossy floor.  Every now and then a monkey or two swings from the branches of a nearby tree to the south, paying little notice to the goings-on below."
  ],
  "image": null,
  "climate": null,
  "title": [
    "[Monastery Ruins, Peace Garden]"
  ],
  "check_location": null,
  "timeto": {
    "21099": 0.2
  },
  "id": 21104,
  "location": "Mist Harbor",
  "tags": [

  ],
  "unique_loot": null,
  "links": [

  ]
}