{
  "id": 21818,
  "title": [
    "[Talador, Old Battlefield]"
  ],
  "description": [
    "A partial skull of what appears to be an orc juts out from the dirt and grass, its surface bleached from long exposure to the sun.  A carrion crow circles overhead, squawking loudly."
  ],
  "paths": [
    "Obvious paths: north, east, west"
  ],
  "location": "Talador",
  "wayto": {
    "21817": "east",
    "21819": "west",
    "21848": "north"
  },
  "timeto": {
    "21817": 0.2,
    "21819": 0.2,
    "21848": 0.2
  },
  "image": "wl-talador-west-1392305660.png",
  "image_coords": [
    487,
    172,
    501,
    186
  ]
}