{
  "id": 22267,
  "title": [
    "[Mestanir, Westgreen Street]"
  ],
  "description": [
    "A small enclave of cabins circles a stone fountain just to the west, each of the wooden dwellings identical in shape.  The open lawns of each cabin are meticulously tended and vibrant."
  ],
  "paths": [
    "Obvious paths: north"
  ],
  "location": "the city of Mestanir",
  "wayto": {
    "22266": "north"
  },
  "timeto": {
    "22266": 0.2
  },
  "image": "wl-swale-1405616532.png",
  "image_coords": [
    65,
    238,
    78,
    253
  ]
}