{
  "id": 24781,
  "title": [
    "[Helden Hall, Hot Tub]"
  ],
  "description": [
    "The hot water feels soothing against your skin as you enter the tub.  The bubbles surround your body, and you feel your troubles and worries melting away.  Your muscles begin to relax as you let yourself slide deeper still into the hot bubbly water."
  ],
  "paths": [
    "Obvious paths: out"
  ],
  "location": "Wehnimer's Landing",
  "wayto": {
    "24774": "swim out"
  },
  "timeto": {
    "24774": 0.2
  },
  "image": "wl-heldenhall-1502386358.png",
  "image_coords": [
    737,
    301,
    773,
    335
  ]
}