{
  "id": 25082,
  "title": [
    "[Reim Settlement, Barracks]"
  ],
  "description": [
    "A row of beds covered with green woolen blankets lines the far wall.  Narrow cots are mounted above the beds with wooden supports.  In front of each bed is a low metal locker latched with a bulbous, iron lock.  Small tables are spaced between each sleeping area, all set with an assortment of neatly organized personal effects."
  ],
  "paths": [
    "Obvious exits: southeast"
  ],
  "location": "the Settlement of Reim",
  "wayto": {
    "24965": "southeast"
  },
  "timeto": {
    "24965": 0.2
  },
  "image": "imt-Reim-1260914759.png",
  "image_coords": [
    440,
    474,
    453,
    486
  ]
}