{
  "wayto": {
    "2512": "9e4da08482f40ad3b7912f194ff7af3d",
    "2514": "a1bd023500a3a9633d7c708d74ed9e8f"
  },
  "paths": [
    "Obvious paths: south, northwest"
  ],
  "image_coords": [
    1170,
    415,
    1180,
    425
  ],
  "terrain": null,
  "description": [
    "The icy trail skirts the very edge of the deadly, partially frozen marsh.  Beside the trail lies the dead carcass of some unidentifiable animal--mute evidence that the marsh should be avoided at all costs."
  ],
  "image": "imt-trail-1264234799.png",
  "climate": null,
  "title": [
    "[Icemule Trail, Tundra]"
  ],
  "check_location": null,
  "timeto": {
    "2512": 0.2,
    "2514": 0.2
  },
  "id": 2513,
  "location": "the Icemule Trail",
  "tags": [
    "snow pansy",
    "arctic moss",
    "broken twig",
    "ironfern root"
  ],
  "links": [

  ]
}