{
  "id": 28647,
  "title": [
    "[Voln Tapestry Table]"
  ],
  "description": [
    "The tapestry hanging behind the table depicts the god Voln, The Liberator.  He is dressed in black chain mail covered in a white surcoat.  In his hand is a white shield etched with faint images of souls floating upward, as if newly released from the rotting corpses beneath them."
  ],
  "paths": [
    "Obvious exits: out"
  ],
  "location": "Wehnimer's Landing",
  "wayto": {
    "21747": "out"
  },
  "timeto": {
    "21747": 0.2
  }
}