{
  "wayto": {
    "14330": "out"
  },
  "paths": [
    "Obvious exits: out"
  ],
  "image_coords": null,
  "terrain": null,
  "description": [
    "Mismatched wooden chairs are pushed haphazardly up against the long wooden table that has been darkened with age and use.  A painting of a large-mouthed sea bass can still be seen on the table surface, discernable through all the marks and stains."
  ],
  "image": null,
  "climate": null,
  "title": [
    "[Burnt Bass Table]"
  ],
  "check_location": null,
  "timeto": {
    "14330": 0.2
  },
  "id": 28687,
  "location": "Solhaven",
  "tags": [

  ],
  "unique_loot": null
}