{
  "wayto": {
    "3002": "southwest",
    "3000": "west"
  },
  "paths": [
    "Obvious paths: southwest, west"
  ],
  "image_coords": [
    376,
    978,
    386,
    988
  ],
  "terrain": "mountainous",
  "description": [
    "A deep snowfield blocks passage to the east, sparkling brightly with a fresh layer of snow.  Small stones scatter the ground, their edges worn smooth by years of cold and wind."
  ],
  "image": "imt-east_west_north_gates-1264234799.png",
  "climate": "glacial",
  "title": [
    "[Arctic Tundra, High Plain]"
  ],
  "check_location": null,
  "timeto": {
    "3002": 0.2,
    "3000": 0.2
  },
  "id": 3001,
  "location": "the High Plains",
  "tags": [
    "some valerian root",
    "red winterberry",
    "silverback orc",
    "sweetfern stalk",
    "sassafras leaf",
    "angelica root",
    "pennyroyal stem",
    "winter rose",
    "arctic moss",
    "calamintha blossom",
    "snowberries",
    "pale thornberry",
    "small loganberry",
    "ironfern root",
    "valerian root",
    "meta:forage-sensed"
  ],
  "links": [

  ]
}