{
  "wayto": {
    "15538": "go tower",
    "618": "out"
  },
  "paths": [
    "Obvious paths: out"
  ],
  "image_coords": [
    875,
    143,
    898,
    165
  ],
  "terrain": "cultivated",
  "description": [
    "Flanked by a small hill of verdant green grass, a massive spire of silver-sheened crystal rises up amid the tall rooftops of the city, its surface sparkling and pristine.  A white walkway leads up to the base of the tower, yet its flawless walls offer no obvious means of access.  A ring of identical silver monoliths encircle the tower, and a scarlet circle of runes is scribed into the soft earth at the end of the walkway."
  ],
  "image": "en-ta_illistim-new.jpg",
  "climate": "temperate",
  "title": [
    "[Wizard Guild, Courtyard]"
  ],
  "check_location": null,
  "timeto": {
    "15538": 0.2,
    "618": 0.2
  },
  "id": 4026,
  "location": "Ta'Illistim",
  "tags": [
    "wizardguild",
    "cactacae spine",
    "calamia fruit",
    "haphip root",
    "sovyn clove",
    "small flower",
    "small rose",
    "small daisy",
    "angelica root",
    "trollfear mushroom",
    "soft white mushroom",
    "withered black mushroom",
    "daggerstalk mushroom",
    "flathead mushroom",
    "genkew mushroom",
    "blue trafel mushroom",
    "small violet",
    "heath aster",
    "golden buttercup",
    "Imaera's Lace",
    "ear of corn",
    "fennel bulb",
    "fig",
    "mustard seeds",
    "rose-marrow root",
    "thyme",
    "small turnip",
    "stalk of wormwood",
    "motherwort",
    "small anemone",
    "pink begonia",
    "orange begonia",
    "white begonia",
    "red begonia",
    "blaestonberry blossom",
    "sprig of clematis",
    "sprig of foxglove",
    "stem of freesia flowers",
    "large white gardenia",
    "honeysuckle vine",
    "hosta flower",
    "pink hydrangea",
    "light blue hydrangea",
    "white hydrangea",
    "purple hydrangea",
    "iris blossom",
    "sprig of jasmine",
    "sprig of lavender",
    "stargazer lily",
    "stalk of monkeyflower",
    "sprig of mournbloom",
    "wild pansy blossom",
    "pink peony",
    "white peony",
    "sprig of wild phlox",
    "small primrose",
    "snapdragon stalk",
    "large sunflower",
    "stalk of tuberose",
    "stem of verbena",
    "sprig of boxwood",
    "sprig of holly",
    "raspberries",
    "tendril of vinca",
    "small apple",
    "green olive",
    "juicy plum",
    "white lily",
    "tiger lily",
    "fire lily",
    "blue whortleberry",
    "yew twig",
    "luckbloom blossom",
    "wavepetal blossom",
    "nightbloom blossom",
    "onion skin",
    "meta:forage-sensed"
  ],
  "links": [

  ]
}