{
  "id": 7661,
  "title": [
    "[Sea Cave, Small Passage]"
  ],
  "description": [
    "The walls and ceiling converge at a steep angle, and a faint musty smell adds to the cramped unpleasant feel of the place.  The rocks are dry and cold to the touch."
  ],
  "paths": [
    "Obvious exits: west, up"
  ],
  "location": "the Coastal Cliffs",
  "wayto": {
    "7660": "up",
    "7662": "west"
  },
  "timeto": {
    "7660": 0.2,
    "7662": 0.2
  },
  "image": "wl-coastal_cliffs-1264234799.png",
  "image_coords": [
    808,
    335,
    818,
    345
  ],
  "tags": [
    "shelfae chieftain",
    "ironfern root"
  ]
}