{
  "id": 8402,
  "title": [
    "[Thanatoph Bowels, West Lobe]"
  ],
  "description": [
    "The western wall of the quatrefoil is streaked with undulating waves of flaking blue woad, like rolling seawaves.  The pattern is bordered with hundreds of arcane glyphs, which mimic the painted waves."
  ],
  "paths": [
    "Obvious exits: northeast, east, southeast"
  ],
  "location": "the bowels of Thanatoph",
  "wayto": {
    "8403": "northeast",
    "8415": "east",
    "8401": "southeast"
  },
  "timeto": {
    "8403": 0.2,
    "8415": 0.2,
    "8401": 0.2
  },
  "image": "wl-stronghold-1264234799.png",
  "image_coords": [
    1099,
    642,
    1109,
    652
  ],
  "tags": [
    "some wingstem root",
    "some cave moss",
    "some wolifrew lichen",
    "withered black mushroom"
  ]
}