{
  "wayto": {
    "8546": {
      "stringproc": "1b2d3068c24fc2bce9a4c021a5d03a56"
    },
    "8541": "northwest",
    "8543": "north",
    "8545": "west"
  },
  "paths": [
    "Obvious paths: north, west, northwest"
  ],
  "image_coords": [
    1140,
    678,
    1150,
    688
  ],
  "terrain": "barren scrub",
  "description": [
    "The soaring peak of Zeltoph Mountain looms to the south.  Cloaked in pine trees, the northern base of the mountain rises above the foothills, wearing the zigzag scar of the caravan trail switchbacks."
  ],
  "image": "wl-trollfang-1264234799.png",
  "climate": "cold, dry",
  "title": [
    "[Foothills]"
  ],
  "check_location": null,
  "timeto": {
    "8546": 3.2,
    "8541": 0.2,
    "8543": 0.2,
    "8545": 0.2
  },
  "id": 8544,
  "location": "the foothills of Zeltoph",
  "tags": [
    "some cothinar flower",
    "sprig of larkspur",
    "some wingstem root",
    "moonlight cactus-bloom",
    "stalk of chicory",
    "cothinar flower",
    "wintergreen leaf",
    "bright red teaberry",
    "broken twig",
    "ironfern root",
    "wingstem root",
    "sunburst blossom",
    "meta:forage-sensed"
  ],
  "links": [

  ]
}