{
  "id": 9036,
  "title": [
    "[Vornavis, Wooded Plains]"
  ],
  "description": [
    "Moths and fireflies flit about this area of woodland, moving from bush to bush in breathtaking displays of light and motion.  Many of the bushes here have no leaves, and many empty cocoons can be found hanging from tree branches and bush limbs.",
    "Moths and butterflies flit about this area of woodland, moving from bush to bush in breathtaking displays of color and motion.  Many of the bushes here have no leaves, and many empty cocoons can be found hanging from tree branches and bush limbs."
  ],
  "paths": [
    "Obvious paths: north, southwest"
  ],
  "location": "the plains of Vornavis",
  "wayto": {
    "9035": "southwest",
    "9037": "north"
  },
  "timeto": {
    "9035": 0.2,
    "9037": 0.2
  },
  "image": "vo-caravansary-1264234799.png",
  "image_coords": [
    667,
    167,
    677,
    177
  ],
  "tags": [
    "tkaro root",
    "sprig of wild lilac",
    "some alder bark",
    "some tree bark",
    "some basal moss",
    "some calamia fruit",
    "slender twig",
    "broken twig",
    "oak twig"
  ]
}